PKG-INFO
pyproject.toml
giayolo/__init__.py
giayolo/__version__.py
giayolo/YoloxModels/best_ckpt.pth
giayolo/YoloxModels/combat.pt
giayolo-0.0.3.dist-info/METADATA
giayolo-0.0.3.dist-info/WHEEL
giayolo-0.0.3.dist-info/RECORD
