Metadata-Version: 2.3
Name: giayolo
Version: 0.0.3
Summary: AI Model for GIA.
Author: Infstellar
Classifier: License :: OSI Approved :: MIT License
Classifier: Operating System :: OS Independent
Classifier: Programming Language :: Python :: 3
Requires-Python: >=3.7
